callback/__init__.py
callback/consumer.py
callback/handler.py
callback/myscale_callback.py
callback/span_data.py
callback/task_manager.py
myscale_callback/__init__.py
myscale_callback/consumer.py
myscale_callback/handler.py
myscale_callback/span_data.py
myscale_callback/task_manager.py
myscale_callback-0.2.0.dist-info/LICENSE
myscale_callback-0.2.0.dist-info/METADATA
myscale_callback-0.2.0.dist-info/WHEEL
myscale_callback-0.2.0.dist-info/top_level.txt
myscale_callback-0.2.0.dist-info/RECORD
