Metadata-Version: 2.1
Name: myscale-callback
Version: 0.2.0
Summary: A package for MyScale Callback Handler
Home-page: https://github.com/myscale/myscale_callback.git
Author: Xu Jing
Author-email: xuj@myscale.com
Classifier: Programming Language :: Python :: 3
Classifier: License :: OSI Approved :: MIT License
Classifier: Operating System :: OS Independent
Requires-Python: >=3.10
License-File: LICENSE
Requires-Dist: backoff (>=2.2.1)
Requires-Dist: langchain (>=0.2.0)
Requires-Dist: langchain-community (>=0.2.0)
Requires-Dist: clickhouse-connect (>=0.7.8)
